TT_MongoDB/__init__.py
TT_MongoDB/mongodb_connection.py
TT_MongoDB-0.2.0.dist-info/METADATA
TT_MongoDB-0.2.0.dist-info/WHEEL
TT_MongoDB-0.2.0.dist-info/top_level.txt
TT_MongoDB-0.2.0.dist-info/RECORD
