Metadata-Version: 2.1
Name: TT-MongoDB
Version: 0.2.0
Summary: A MongoDB connection utility for Python applications,                  providing streamlined and easy-to-use interfaces for connecting                  to MongoDB databases, executing queries, and managing database operations.                  Supports parallel queries and integrates seamlessly with MongoDB's native features,                 including authentication and collection management.
Home-page: UNKNOWN
Author: Zyad Samy
Author-email: zyad.samy@twentytoo.ai
License: UNKNOWN
Platform: UNKNOWN
Classifier: Programming Language :: Python :: 3
Classifier: Operating System :: OS Independent
Requires-Python: >=3.6
Requires-Dist: pymongo >=3.10.1
